Metadata-Version: 2.1
Name: pitonbr
Version: 1.0.0
Summary: A biblioteca Píton é uma ferramenta educacional para falantes de português que desejam aprender programação em Python. Com sintaxe próxima ao Portugol, ela oferece uma abordagem amigável e acessível, tornando o aprendizado de algoritmos e lógica de programação mais acessível para quem tem dificuldades com o inglês.
Home-page: https://github.com/duxtec/piton
Author: Dux Tecnologia
Author-email: contato@dux.tec.br
License: UNKNOWN
Platform: UNKNOWN
Classifier: Development Status :: 3 - Alpha
Classifier: Intended Audience :: Education
Classifier: License :: OSI Approved :: GNU General Public License v3 (GPLv3)
Classifier: Programming Language :: Python :: 3
Classifier: Programming Language :: Python :: 3.6
Classifier: Programming Language :: Python :: 3.7
Classifier: Programming Language :: Python :: 3.8
Classifier: Programming Language :: Python :: 3.9
License-File: LICENSE
